sdypy_template_project/__init__.py
sdypy_template_project/__main__.py
sdypy_template_project/core.py
sdypy_template_project/open_sd_klemen.py
sdypy_template_project/opensd_lorenzo.py
sdypy_template_project/prova.py
sdypy_template_project/visualize.py
opensd2025_track4-0.1.2.dist-info/METADATA
opensd2025_track4-0.1.2.dist-info/WHEEL
opensd2025_track4-0.1.2.dist-info/RECORD
