Metadata-Version: 2.4
Name: opensd2025_track4
Version: 0.1.2
Summary: A template for SDyPy projects.
Project-URL: homepage, https://github.com/klemengit/OpenSD2025_repo
Project-URL: documentation, https://opensd2025-repo.readthedocs.io/en/latest/
Project-URL: source, https://github.com/klemengit/OpenSD2025_repo
Author-email: "Janko Slavič et al." <janko.slavic@fs.uni-lj.si>
Maintainer-email: "Janko Slavič et al." <janko.slavic@fs.uni-lj.si>
License-Expression: MIT
Keywords: sdypy,template
Classifier: Development Status :: 5 - Production/Stable
Classifier: Intended Audience :: Developers
Classifier: License :: OSI Approved :: MIT License
Classifier: Programming Language :: Python :: 3.10
Classifier: Topic :: Scientific/Engineering
Requires-Python: >=3.10
Requires-Dist: matplotlib>=3.0.0
Requires-Dist: numpy>=1.11.0
Requires-Dist: pymraw>=0.2.0
Requires-Dist: scipy>=1.2.0
Requires-Dist: tqdm>=4.25.0
Provides-Extra: dev
Requires-Dist: build; extra == 'dev'
Requires-Dist: pytest; extra == 'dev'
Requires-Dist: sphinx; extra == 'dev'
Requires-Dist: sphinx-copybutton>=0.5.2; extra == 'dev'
Requires-Dist: sphinx-rtd-theme; extra == 'dev'
Requires-Dist: twine; extra == 'dev'
Requires-Dist: wheel; extra == 'dev'
